gitlab/__init__.py
gitlab/__main__.py
gitlab/_version.py
gitlab/base.py
gitlab/cli.py
gitlab/client.py
gitlab/config.py
gitlab/const.py
gitlab/exceptions.py
gitlab/mixins.py
gitlab/py.typed
gitlab/types.py
gitlab/utils.py
gitlab/_backends/__init__.py
gitlab/_backends/graphql.py
gitlab/_backends/protocol.py
gitlab/_backends/requests_backend.py
gitlab/v4/__init__.py
gitlab/v4/cli.py
gitlab/v4/objects/__init__.py
gitlab/v4/objects/access_requests.py
gitlab/v4/objects/appearance.py
gitlab/v4/objects/applications.py
gitlab/v4/objects/artifacts.py
gitlab/v4/objects/audit_events.py
gitlab/v4/objects/award_emojis.py
gitlab/v4/objects/badges.py
gitlab/v4/objects/boards.py
gitlab/v4/objects/branches.py
gitlab/v4/objects/broadcast_messages.py
gitlab/v4/objects/bulk_imports.py
gitlab/v4/objects/ci_lint.py
gitlab/v4/objects/cluster_agents.py
gitlab/v4/objects/clusters.py
gitlab/v4/objects/commits.py
gitlab/v4/objects/container_registry.py
gitlab/v4/objects/custom_attributes.py
gitlab/v4/objects/deploy_keys.py
gitlab/v4/objects/deploy_tokens.py
gitlab/v4/objects/deployments.py
gitlab/v4/objects/discussions.py
gitlab/v4/objects/draft_notes.py
gitlab/v4/objects/environments.py
gitlab/v4/objects/epics.py
gitlab/v4/objects/events.py
gitlab/v4/objects/export_import.py
gitlab/v4/objects/features.py
gitlab/v4/objects/files.py
gitlab/v4/objects/geo_nodes.py
gitlab/v4/objects/group_access_tokens.py
gitlab/v4/objects/groups.py
gitlab/v4/objects/hooks.py
gitlab/v4/objects/integrations.py
gitlab/v4/objects/invitations.py
gitlab/v4/objects/issues.py
gitlab/v4/objects/iterations.py
gitlab/v4/objects/job_token_scope.py
gitlab/v4/objects/jobs.py
gitlab/v4/objects/keys.py
gitlab/v4/objects/labels.py
gitlab/v4/objects/ldap.py
gitlab/v4/objects/members.py
gitlab/v4/objects/merge_request_approvals.py
gitlab/v4/objects/merge_requests.py
gitlab/v4/objects/merge_trains.py
gitlab/v4/objects/milestones.py
gitlab/v4/objects/namespaces.py
gitlab/v4/objects/notes.py
python_gitlab-5.2.0.dist-info/AUTHORS
python_gitlab-5.2.0.dist-info/COPYING
python_gitlab-5.2.0.dist-info/METADATA
python_gitlab-5.2.0.dist-info/WHEEL
python_gitlab-5.2.0.dist-info/entry_points.txt
python_gitlab-5.2.0.dist-info/top_level.txt
python_gitlab-5.2.0.dist-info/RECORD
