Metadata-Version: 2.1
Name: python-gitlab
Version: 5.2.0
Summary: The python wrapper for the GitLab REST and GraphQL APIs.
Author-email: Gauvain Pocentek <gauvain@pocentek.net>
Maintainer-email: John Villalovos <john@sodarock.com>, Max Wittig <max.wittig@siemens.com>, Nejc Habjan <nejc.habjan@siemens.com>, Roger Meier <r.meier@siemens.com>
License: LGPL-3.0-or-later
Project-URL: Homepage, https://github.com/python-gitlab/python-gitlab
Project-URL: Changelog, https://github.com/python-gitlab/python-gitlab/blob/main/CHANGELOG.md
Project-URL: Documentation, https://python-gitlab.readthedocs.io
Project-URL: Source, https://github.com/python-gitlab/python-gitlab
Keywords: api,client,gitlab,python,python-gitlab,wrapper
Classifier: Development Status :: 5 - Production/Stable
Classifier: Environment :: Console
Classifier: Intended Audience :: System Administrators
Classifier: License :: OSI Approved :: GNU Lesser General Public License v3 (LGPLv3)
Classifier: Natural Language :: English
Classifier: Operating System :: POSIX
Classifier: Operating System :: Microsoft :: Windows
Classifier: Programming Language :: Python
Classifier: Programming Language :: Python :: 3
Classifier: Programming Language :: Python :: 3.9
Classifier: Programming Language :: Python :: 3.10
Classifier: Programming Language :: Python :: 3.11
Classifier: Programming Language :: Python :: 3.12
Classifier: Programming Language :: Python :: 3.13
Requires-Python: >=3.9.0
License-File: COPYING
License-File: AUTHORS
Requires-Dist: requests>=2.32.0
Requires-Dist: requests-toolbelt>=1.0.0
Provides-Extra: autocompletion
Requires-Dist: argcomplete<3,>=1.10.0; extra == "autocompletion"
Provides-Extra: yaml
Requires-Dist: PyYaml>=6.0.1; extra == "yaml"
Provides-Extra: graphql
Requires-Dist: gql[httpx]<4,>=3.5.0; extra == "graphql"
